LICENSE
MANIFEST.in
README.md
setup.cfg
setup.py
graphsim/__init__.py
graphsim.egg-info/PKG-INFO
graphsim.egg-info/SOURCES.txt
graphsim.egg-info/dependency_links.txt
graphsim.egg-info/requires.txt
graphsim.egg-info/top_level.txt
graphsim/iter/ASCOS.py
graphsim/iter/BVD04.py
graphsim/iter/HITS.py
graphsim/iter/HS03.py
graphsim/iter/SimCpl.py
graphsim/iter/SimFld.py
graphsim/iter/SimRank.py
graphsim/iter/TACSim.py
graphsim/iter/TACSim_in_C.py
graphsim/iter/__init__.py
libtacsim/README.md
libtacsim/SConstruct
libtacsim/libtacsim/main.c
libtacsim/libtacsim/tacsim.c
libtacsim/libtacsim/tacsim.h