Metadata-Version: 1.1
Name: graphsim
Version: 0.2.11
Summary: Graph similarity algorithms based on NetworkX.
Home-page: https://github.com/caesar0301/graphsim
Author: Xiaming Chen
Author-email: chenxm35@gmail.com
License: BSC License
Keywords: graph,graph similarity,graph matching
Platform: UNKNOWN
Classifier: Development Status :: 4 - Beta
Classifier: Environment :: Console
Classifier: Intended Audience :: Developers
Classifier: License :: Freely Distributable
Classifier: Operating System :: OS Independent
Classifier: Programming Language :: Python
Classifier: Programming Language :: Python :: 2.7
Classifier: Programming Language :: Python :: 3.3
Classifier: Programming Language :: Python :: 3.4
Classifier: Topic :: Software Development :: Libraries :: Python Modules
